easy_playlist/__init__.py
easy_playlist/playlist.py
easy_playlist-1.9.1.dist-info/LICENSE
easy_playlist-1.9.1.dist-info/METADATA
easy_playlist-1.9.1.dist-info/WHEEL
easy_playlist-1.9.1.dist-info/top_level.txt
easy_playlist-1.9.1.dist-info/RECORD
