Metadata-Version: 2.2
Name: easy-playlist
Version: 1.9.1
Summary: A library to easily manage your playlists in python
Home-page: https://github.com/ThePhoenix78/easy-playlist
Download-URL: https://github.com/ThePhoenix78/easy-playlist/tarball/master
Author: ThePhoenix78
Author-email: thephoenix788@gmail.com
License: MIT
Keywords: playlist,music,timer
Classifier: Programming Language :: Python :: 3
Classifier: License :: OSI Approved :: MIT License
Classifier: Operating System :: OS Independent
License-File: LICENSE
Requires-Dist: ffmpeg-python
Dynamic: author
Dynamic: author-email
Dynamic: classifier
Dynamic: description
Dynamic: description-content-type
Dynamic: download-url
Dynamic: home-page
Dynamic: keywords
Dynamic: license
Dynamic: requires-dist
Dynamic: summary
